Topsis_SaumyaKumari_102303161/__init__.py
Topsis_SaumyaKumari_102303161/topsis.py
topsis_saumyakumari_102303161-1.0.2.dist-info/METADATA
topsis_saumyakumari_102303161-1.0.2.dist-info/WHEEL
topsis_saumyakumari_102303161-1.0.2.dist-info/entry_points.txt
topsis_saumyakumari_102303161-1.0.2.dist-info/top_level.txt
topsis_saumyakumari_102303161-1.0.2.dist-info/RECORD
