Metadata-Version: 2.1
Name: topsis-saumyakumari-102303161
Version: 1.0.2
Summary: Python package for TOPSIS method
Author: Saumya Kumari
Requires-Python: >=3.6
